README.md
setup.py
AiCoreSentimentStockScraper.egg-info/PKG-INFO
AiCoreSentimentStockScraper.egg-info/SOURCES.txt
AiCoreSentimentStockScraper.egg-info/dependency_links.txt
AiCoreSentimentStockScraper.egg-info/requires.txt
AiCoreSentimentStockScraper.egg-info/top_level.txt
stock_scraper_AiCore/Sentiment_analysis.py
stock_scraper_AiCore/__init__.py
stock_scraper_AiCore/__main__.py
stock_scraper_AiCore/config.py
stock_scraper_AiCore/data_base.py
stock_scraper_AiCore/process.py
stock_scraper_AiCore/stock_scraper.py
test/__init__.py
test/test_data_base.py
test/test_process.py
test/test_stock_scraper.py