Metadata-Version: 1.0
Name: AiCoreSentimentStockScraper
Version: 0.0.4
Summary: scraping stock data
Home-page: UNKNOWN
Author: Tamim Ehsan
Author-email: UNKNOWN
License: MIT
Platform: UNKNOWN
